wrapped_optimizations/__init__.py
wrapped_optimizations/wrapped_optimizations.py
wrapped_optimizations-0.1.2.dist-info/LICENSE
wrapped_optimizations-0.1.2.dist-info/METADATA
wrapped_optimizations-0.1.2.dist-info/WHEEL
wrapped_optimizations-0.1.2.dist-info/top_level.txt
wrapped_optimizations-0.1.2.dist-info/RECORD
