Metadata-Version: 2.1
Name: wrapped_optimizations
Version: 0.1.2
Summary: A wrapper around some of scipy's optimization functions to allow for a more convenient use of parameters and constants.
Home-page: https://github.com/stephtr/wrapped-optimizations
Author: Stephan Troyer
Author-email: stephantroyer@live.at
License-File: LICENSE
Requires-Dist: numpy
Requires-Dist: scipy
